MANIFEST.in
README.txt
setup.py
.hg/cur-message.txt
.hg/last-message.txt
arff/__init__.py
arff.egg-info/PKG-INFO
arff.egg-info/SOURCES.txt
arff.egg-info/dependency_links.txt
arff.egg-info/top_level.txt