Metadata-Version: 1.0
Name: arff
Version: 0.7
Summary: Python package for reading and writing Weka arff files
Home-page: http://code.google.com/p/arff/
Author: ubershmekel
Author-email: ubershmekel@gmail.com
License: UNKNOWN
Platform: UNKNOWN
Classifier: Development Status :: 4 - Beta
Classifier: Intended Audience :: Developers
Classifier: License :: OSI Approved :: BSD License
Classifier: Operating System :: OS Independent
Classifier: Programming Language :: Python :: 2
Classifier: Programming Language :: Python :: 3
Classifier: Topic :: Utilities
Classifier: Topic :: Software Development :: Libraries :: Python Modules
